README
setup.py
flylog2/__init__.py
flylog2/constants.py
flylog2.egg-info/PKG-INFO
flylog2.egg-info/SOURCES.txt
flylog2.egg-info/dependency_links.txt
flylog2.egg-info/requires.txt
flylog2.egg-info/top_level.txt
flylog2/api/__init__.py
flylog2/api/client.py
flylog2/api/log_handler.py
flylog2/server/__init__.py
flylog2/server/log.py
flylog2/server/server.py
flylog2/server/utils.py
flylog2/server/backends/__init__.py
flylog2/server/backends/ding.py
flylog2/server/backends/mail.py
flylog2/server/backends/sendcloud.py
flylog2/server/backends/tg.py