Metadata-Version: 1.0
Name: flylog2
Version: 0.1.90
Summary: make log fly to mail or other
Home-page: https://github.com/dantezhu/flylog
Author: grey
Author-email: greyeee@gmail.com
License: UNKNOWN
Platform: UNKNOWN
